xy_dict/Dict.py
xy_dict/ModuleData.py
xy_dict/Resource.py
xy_dict/__init__.py
xy_dict/utils.py
xy_dict/execute/Main.py
xy_dict/execute/__init__.py
xy_dict-1.0.7.dist-info/LICENSE
xy_dict-1.0.7.dist-info/METADATA
xy_dict-1.0.7.dist-info/WHEEL
xy_dict-1.0.7.dist-info/top_level.txt
xy_dict-1.0.7.dist-info/RECORD
