Metadata-Version: 2.1
Name: xy_dict
Version: 1.0.7
Summary: xy_dict 模块
Author-email: yuyangit <yuyangit.0515@qq.com>
Classifier: Programming Language :: Python :: 3
Requires-Python: >=3.11.3
License-File: LICENSE
